LICENSE
MANIFEST.in
README.txt
setup.cfg
setup.py
pbp/__init__.py
pbp.buildbotenv.egg-info/PKG-INFO
pbp.buildbotenv.egg-info/SOURCES.txt
pbp.buildbotenv.egg-info/dependency_links.txt
pbp.buildbotenv.egg-info/namespace_packages.txt
pbp.buildbotenv.egg-info/not-zip-safe
pbp.buildbotenv.egg-info/requires.txt
pbp.buildbotenv.egg-info/top_level.txt
pbp/buildbotenv/__init__.py