Metadata-Version: 1.0
Name: pbp.buildbotenv
Version: 0.2.0
Summary: Python Expert Programming - Buildbot environment
Home-page: http://atomisator.ziade.org
Author: Tarek Ziadé
Author-email: tarek@ziade.org
License: GPL
Platform: UNKNOWN
Classifier: Programming Language :: Python
Classifier: Topic :: Software Development :: Libraries :: Python Modules
